{
  "user": [
    {
      "id": 1,
      "email": "marcos.x.marcos@hotmail.com",
      "nome": "Marcos Bento",
      "senha": "ssxyjjirf97",
      "imagem": ""
    },
    {
      "email": "fabio_albarelli@hotmail.com",
      "nome": "Fabio Albarelli",
      "senha": "ssxyjjirf97",
      "id": 2
    }
  ],
  "chats": [
    {
      "chat_id": 1,
      "user_1_id": 1,
      "user_2_id": 2,
      "content": [
        {
          "message_id": 1,
          "user": "Fabio Albareli",
          "time": "20:18",
          "chat": "Você jogou aquele jogo da memória?"
        },
        {
          "message_id": 2,
          "user": "Marcos Bento",
          "time": "20:20",
          "chat": "Joguei sim e curti bastante o jogo, meus sobrinhos também adoraram!"
        },
        {
          "message_id": 3,
          "user": "Fabio Albareli",
          "time": "20:20",
          "chat": "Será que tem alguma novidade saindo?"
        },
        {
          "message_id": 4,
          "user": "Fabio Albareli",
          "time": "20:22",
          "chat": "E voCê viu o último lançamento? Vai sair em Dezembro..."
        }
      ]
    }
  ]
}